{
  "info": {
    "name": "NetworkCode API",
    "description": "Complete CRUD operations for Network Codes",
    "schema": "https://schema.getpostman.com/json/collection/v2.1.0/collection.json"
  },
  "auth": {
    "type": "bearer",
    "bearer": [
      {
        "key": "token",
        "value": "{{authToken}}",
        "type": "string"
      }
    ]
  },
  "item": [
    {
      "name": "Create Network Code",
      "request": {
        "method": "POST",
        "header": [
          {
            "key": "Content-Type",
            "value": "application/json"
          }
        ],
        "body": {
          "mode": "raw",
          "raw": "{\n  \"name\": \"Tech Startup Network\",\n  \"codeId\": \"TSN2024\",\n  \"description\": \"A network for tech startups and entrepreneurs\",\n  \"keywords\": [\"tech\", \"startup\", \"innovation\", \"entrepreneurship\"],\n  \"autoConnect\": false,\n  \"expirationTime\": \"2025-12-31T23:59:59.000Z\"\n}"
        },
        "url": {
          "raw": "{{baseUrl}}/network-codes",
          "host": ["{{baseUrl}}"],
          "path": ["network-codes"]
        },
        "description": "Create a new network code with all details"
      },
      "response": []
    },
    {
      "name": "Get All Network Codes",
      "request": {
        "method": "GET",
        "header": [],
        "url": {
          "raw": "{{baseUrl}}/network-codes",
          "host": ["{{baseUrl}}"],
          "path": ["network-codes"]
        },
        "description": "Get all network codes without any filters"
      },
      "response": []
    },
    {
      "name": "Get Network Codes - Filter by Keyword",
      "request": {
        "method": "GET",
        "header": [],
        "url": {
          "raw": "{{baseUrl}}/network-codes?keyword=tech",
          "host": ["{{baseUrl}}"],
          "path": ["network-codes"],
          "query": [
            {
              "key": "keyword",
              "value": "tech"
            }
          ]
        },
        "description": "Get network codes filtered by a specific keyword"
      },
      "response": []
    },
    {
      "name": "Get Network Codes - Filter by AutoConnect",
      "request": {
        "method": "GET",
        "header": [],
        "url": {
          "raw": "{{baseUrl}}/network-codes?autoConnect=true",
          "host": ["{{baseUrl}}"],
          "path": ["network-codes"],
          "query": [
            {
              "key": "autoConnect",
              "value": "true"
            }
          ]
        },
        "description": "Get network codes that have autoConnect enabled"
      },
      "response": []
    },
    {
      "name": "Get Network Codes - Active Only",
      "request": {
        "method": "GET",
        "header": [],
        "url": {
          "raw": "{{baseUrl}}/network-codes?active=true",
          "host": ["{{baseUrl}}"],
          "path": ["network-codes"],
          "query": [
            {
              "key": "active",
              "value": "true"
            }
          ]
        },
        "description": "Get only active network codes (not expired)"
      },
      "response": []
    },
    {
      "name": "Get Network Code by CodeId",
      "request": {
        "method": "GET",
        "header": [],
        "url": {
          "raw": "{{baseUrl}}/network-codes/TSN2024",
          "host": ["{{baseUrl}}"],
          "path": ["network-codes", "TSN2024"]
        },
        "description": "Get a specific network code by its codeId"
      },
      "response": []
    },
    {
      "name": "Update Network Code",
      "request": {
        "method": "PUT",
        "header": [
          {
            "key": "Content-Type",
            "value": "application/json"
          }
        ],
        "body": {
          "mode": "raw",
          "raw": "{\n  \"name\": \"Tech Startup Network - Updated\",\n  \"description\": \"Updated description for tech startup network\",\n  \"keywords\": [\"tech\", \"startup\", \"innovation\", \"AI\", \"SaaS\"],\n  \"autoConnect\": true,\n  \"expirationTime\": \"2026-12-31T23:59:59.000Z\"\n}"
        },
        "url": {
          "raw": "{{baseUrl}}/network-codes/TSN2024",
          "host": ["{{baseUrl}}"],
          "path": ["network-codes", "TSN2024"]
        },
        "description": "Update an existing network code"
      },
      "response": []
    },
    {
      "name": "Search Network Codes",
      "request": {
        "method": "POST",
        "header": [
          {
            "key": "Content-Type",
            "value": "application/json"
          }
        ],
        "body": {
          "mode": "raw",
          "raw": "{\n  \"searchTerm\": \"startup\"\n}"
        },
        "url": {
          "raw": "{{baseUrl}}/network-codes/search",
          "host": ["{{baseUrl}}"],
          "path": ["network-codes", "search"]
        },
        "description": "Search network codes by name, description, or keywords"
      },
      "response": []
    },
    {
      "name": "Delete Network Code",
      "request": {
        "method": "DELETE",
        "header": [],
        "url": {
          "raw": "{{baseUrl}}/network-codes/TSN2024",
          "host": ["{{baseUrl}}"],
          "path": ["network-codes", "TSN2024"]
        },
        "description": "Delete a network code by its codeId"
      },
      "response": []
    },
    {
      "name": "Get Network Codes - Filter by UserId",
      "request": {
        "method": "GET",
        "header": [],
        "url": {
          "raw": "{{baseUrl}}/network-codes?userId=64b8f1234567890abcdef123",
          "host": ["{{baseUrl}}"],
          "path": ["network-codes"],
          "query": [
            {
              "key": "userId",
              "value": "64b8f1234567890abcdef123"
            }
          ]
        },
        "description": "Get network codes for a specific user"
      },
      "response": []
    },
    {
      "name": "Get Network Codes by User ID",
      "request": {
        "method": "GET",
        "header": [],
        "url": {
          "raw": "{{baseUrl}}/network-codes/user/64b8f1234567890abcdef123",
          "host": ["{{baseUrl}}"],
          "path": ["network-codes", "user", "64b8f1234567890abcdef123"]
        },
        "description": "Get all network codes for a specific user by userId"
      },
      "response": []
    },
    {
      "name": "Search Network Codes with UserId Filter",
      "request": {
        "method": "POST",
        "header": [
          {
            "key": "Content-Type",
            "value": "application/json"
          }
        ],
        "body": {
          "mode": "raw",
          "raw": "{\n  \"searchTerm\": \"startup\",\n  \"userId\": \"64b8f1234567890abcdef123\"\n}"
        },
        "url": {
          "raw": "{{baseUrl}}/network-codes/search",
          "host": ["{{baseUrl}}"],
          "path": ["network-codes", "search"]
        },
        "description": "Search network codes for a specific user"
      },
      "response": []
    },
    {
      "name": "Get QR Code for Network Code",
      "request": {
        "method": "GET",
        "header": [],
        "url": {
          "raw": "{{baseUrl}}/network-codes/TSN2024/qr",
          "host": ["{{baseUrl}}"],
          "path": ["network-codes", "TSN2024", "qr"]
        },
        "description": "Get QR code URL and details for a specific network code (public endpoint)"
      },
      "response": []
    }
  ],
  "variable": [
    {
      "key": "baseUrl",
      "value": "http://localhost:3000",
      "type": "string"
    },
    {
      "key": "authToken",
      "value": "your-jwt-token-here",
      "type": "string"
    }
  ]
}
